pyoof/__init__.py
pyoof/_astropy_init.py
pyoof/aux_functions.py
pyoof/beam_generator.py
pyoof/conftest.py
pyoof/fit_beam.py
pyoof/math_functions.py
pyoof/plot_routines.py
pyoof/version.py
pyoof/aperture/__init__.py
pyoof/aperture/aperture.py
pyoof/aperture/tests/__init__.py
pyoof/aperture/tests/setup_package.py
pyoof/aperture/tests/test_aperture.py
pyoof/aperture/tests/data/aperture.npy
pyoof/aperture/tests/data/illum_gauss.npy
pyoof/aperture/tests/data/illum_pedestal.npy
pyoof/aperture/tests/data/phase.npz
pyoof/aperture/tests/data/radiation_pattern.npz
pyoof/aperture/tests/data/wavefront.npy
pyoof/data/config_params.yml
pyoof/data/example0.fits
pyoof/data/pyoof.mplstyle
pyoof/telgeometry/__init__.py
pyoof/telgeometry/telgeometry.py
pyoof/telgeometry/tests/__init__.py
pyoof/telgeometry/tests/setup_package.py
pyoof/telgeometry/tests/test_telgeometry.py
pyoof/telgeometry/tests/data/block_effelsberg.npy
pyoof/telgeometry/tests/data/block_manual.npy
pyoof/telgeometry/tests/data/opd_effelsberg.npy
pyoof/telgeometry/tests/data/opd_manual.npy
pyoof/tests/__init__.py
pyoof/tests/coveragerc
pyoof/tests/setup_package.py
pyoof/tests/test_math_functions.py
pyoof/tests/data/corr_co_matrices.npy
pyoof/tests/data/cov_co_matrices.npy
pyoof/tests/data/jac_co_matrices.npy
pyoof/tests/data/res_co_matrices.npy
pyoof/zernike/__init__.py
pyoof/zernike/zernike.py
pyoof/zernike/tests/__init__.py
pyoof/zernike/tests/setup_package.py
pyoof/zernike/tests/test_zernike.py
pyoof/zernike/tests/data/R.npy
pyoof/zernike/tests/data/U.npy
pyoof-0.2.3.dist-info/DESCRIPTION.rst
pyoof-0.2.3.dist-info/METADATA
pyoof-0.2.3.dist-info/RECORD
pyoof-0.2.3.dist-info/WHEEL
pyoof-0.2.3.dist-info/entry_points.txt
pyoof-0.2.3.dist-info/metadata.json
pyoof-0.2.3.dist-info/top_level.txt
