Metadata-Version: 2.0
Name: pyoof
Version: 0.2.3
Summary: pyoof is a Python package which performs out-of-focus (OOF) holography on astronomical beam maps for single-dish radio telescopes.
Home-page: https://github.com/tcassanelli/pyoof
Author: Tomas Cassanelli
Author-email: tcassanelli@gmail.com
License: BSD
Platform: UNKNOWN
Requires-Dist: astropy
Requires-Dist: scipy
Requires-Dist: matplotlib
Requires-Dist: numpy
Requires-Dist: pytest
Requires-Dist: pyyaml
Requires-Dist: setuptools
